arxiv/base/__init__.py
arxiv/base/agent.py
arxiv/base/alerts.py
arxiv/base/app_tests.py
arxiv/base/config.py
arxiv/base/context_processors.py
arxiv/base/converter.py
arxiv/base/exceptions.py
arxiv/base/factory.py
arxiv/base/filters.py
arxiv/base/globals.py
arxiv/base/logging.py
arxiv/base/routes.py
arxiv/base/middleware/__init__.py
arxiv/base/middleware/base.py
arxiv/base/middleware/request_logs.py
arxiv/base/middleware/tests.py
arxiv/base/static/css/abs.css
arxiv/base/static/css/arxivstyle.css
arxiv/base/static/css/arxivstyle.css.map
arxiv/base/static/fontawesome-svgs/LICENSE.txt
arxiv/base/static/fontawesome-svgs/README.md
arxiv/base/static/fontawesome-svgs/svgs/brands/twitter.svg
arxiv/base/static/fontawesome-svgs/svgs/solid/edit.svg
arxiv/base/static/fontawesome-svgs/svgs/solid/envelope.svg
arxiv/base/static/fontawesome-svgs/svgs/solid/exclamation-circle.svg
arxiv/base/static/fontawesome-svgs/svgs/solid/exclamation-triangle.svg
arxiv/base/static/fontawesome-svgs/svgs/solid/exclamation.svg
arxiv/base/static/fontawesome-svgs/svgs/solid/external-link-alt.svg
arxiv/base/static/fontawesome-svgs/svgs/solid/external-link-square-alt.svg
arxiv/base/static/fontawesome-svgs/svgs/solid/info-circle.svg
arxiv/base/static/fontawesome-svgs/svgs/solid/info.svg
arxiv/base/static/fontawesome-svgs/svgs/solid/pencil-alt.svg
arxiv/base/static/fontawesome-svgs/svgs/solid/question-circle.svg
arxiv/base/static/fontawesome-svgs/svgs/solid/question.svg
arxiv/base/static/fontawesome-svgs/svgs/solid/trash-alt.svg
arxiv/base/static/fontawesome-svgs/svgs/solid/trash-restore-alt.svg
arxiv/base/static/images/CUL-reduced-white-SMALL.svg
arxiv/base/static/images/arxiv-logo-one-color-white.svg
arxiv/base/static/images/arxiv-logo-web.svg
arxiv/base/static/images/arxiv-small.png
arxiv/base/static/images/cornell-reduced-white-SMALL.svg
arxiv/base/static/images/smileybones-error-orange.svg
arxiv/base/static/images/smileybones-error-yellow.svg
arxiv/base/static/images/smileybones.png
arxiv_base-0.17.8.dist-info/LICENSE
arxiv_base-0.17.8.dist-info/METADATA
arxiv_base-0.17.8.dist-info/WHEEL
arxiv_base-0.17.8.dist-info/top_level.txt
arxiv_base-0.17.8.dist-info/RECORD
