Metadata-Version: 2.1
Name: arxiv-base
Version: 0.17.8
Summary: UNKNOWN
Home-page: UNKNOWN
License: UNKNOWN
Platform: UNKNOWN
License-File: LICENSE
Requires-Dist: flask
Requires-Dist: jsonschema
Requires-Dist: pytz
Requires-Dist: uwsgi
Requires-Dist: boto3
Requires-Dist: bleach (==3.3.0)
Requires-Dist: backports-datetime-fromisoformat (==1.0.0)
Requires-Dist: typing-extensions
